Metadata-Version: 1.0
Name: pyscf-qsdopt
Version: 0.1.0
Summary: PySCF extension module qsdopt
Home-page: UNKNOWN
Author: Pyscf Developer
Author-email: UNKNOWN
License: UNKNOWN
Platform: UNKNOWN
